examples/__init__.py
examples/bowling/__init__.py
examples/bowling/start_bowling.py
examples/bowling/test_bowling_functions.py
examples/game_of_life/__init__.py
examples/game_of_life/game_of_life.py
examples/game_of_life/test_game_of_life.py
examples/start_here/__init__.py
examples/start_here/start.py
examples/with_tests/__init__.py
examples/with_tests/start_sample.py
examples/with_tests/test_sample.py
shatter/QM_helper.py
shatter/__init__.py
shatter/code.py
shatter/code_generator.py
shatter/comparison.py
shatter/constants.py
shatter/custom_operator.py
shatter/float_input.py
shatter/float_input_helper.py
shatter/output.py
shatter/processed_rules.py
shatter/qm.py
shatter/rules.py
shatter/solution.py
shatter/solver.py
shatter/tester.py
shatter/machine_learning/__init__.py
shatter/machine_learning/labeled_data.py
shatter/machine_learning/learner.py
shatter/machine_learning/neural_network.py
shatter/machine_learning/util_ml.py
shatter/util/__init__.py
shatter/util/code_dict.py
shatter/util/frozen_dict.py
shatter/util/helpers.py
shatter/util/inverse_tree_set.py
shatter/util/ordered_set.py
shatter-0.6.2.1.dist-info/DESCRIPTION.rst
shatter-0.6.2.1.dist-info/METADATA
shatter-0.6.2.1.dist-info/RECORD
shatter-0.6.2.1.dist-info/WHEEL
shatter-0.6.2.1.dist-info/metadata.json
shatter-0.6.2.1.dist-info/top_level.txt
tests/__init__.py
tests/test_code.py
tests/test_code_equality.py
tests/test_code_generator.py
tests/test_constants.py
tests/test_float_input.py
tests/test_rules.py
tests/test_solver.py
tests/test_tester.py
tests/generated_code/__init__.py
tests/generated_code/code_functions.py
tests/generated_code/code_generator_functions.py
tests/generated_code/float_input_functions.py
tests/generated_code/learner_functions.py
tests/generated_code/solver_functions.py
tests/generated_code/tester_functions.py
tests/machine_learning/__init__.py
tests/machine_learning/test_learner.py
tests/machine_learning/test_neural_network.py
tests/testing_helpers/__init__.py
tests/testing_helpers/common_testing_code.py
tests/testing_helpers/constants.py
tests/util/__init__.py
tests/util/test_helpers.py
tests/util/test_inverse_lexicographical_set.py
