Metadata-Version: 2.0
Name: shatter
Version: 0.6.2.1
Summary: Data Driven Programming
Home-page: https://github.com/jisazaTappsi/shatter
Author: Juan Pablo Isaza
Author-email: biosolardecolombia@gmail.com
License: Copyright (c) 2017 Juan Pablo Isaza
Requires-Dist: Keras (==2.0.6)
Requires-Dist: numpy (==1.13.1)
Requires-Dist: pandas (==0.19.1)
Requires-Dist: pip (==9.0.1)
Requires-Dist: pyeda (==0.28.0)
Requires-Dist: pypandoc (==1.2.0)
Requires-Dist: scikit-learn (==0.19.0)
Requires-Dist: setuptools (==36.0.1)
Requires-Dist: sympy (==1.1)
